pipemesh/__init__.py
pipemesh/gmsh.py
pipemesh/pieces.py
pipemesh/pipes.py
pipemesh/icferst/3d_pipe_FEM.mpml
pipemesh/icferst/__init__.py
pipemesh/icferst/auto_mpml.py
pipemesh/images/abc.png
pipemesh/images/bend.png
pipemesh/images/bend1.png
pipemesh/images/bend2.png
pipemesh/images/change_radius.png
pipemesh/images/cylinder.png
pipemesh/images/downwards_pipe.png
pipemesh/images/hufnagel1.png
pipemesh/images/hufnagel2.png
pipemesh/images/mitered.png
pipemesh/images/mitered1.png
pipemesh/images/mitered2.png
pipemesh/images/network.png
pipemesh/images/network2.png
pipemesh/images/network3.png
pipemesh/images/t_junc.png
pipemesh/images/t_junction.png
pipemesh-1.0.dist-info/LICENSE
pipemesh-1.0.dist-info/METADATA
pipemesh-1.0.dist-info/WHEEL
pipemesh-1.0.dist-info/top_level.txt
pipemesh-1.0.dist-info/RECORD
