Metadata-Version: 2.1
Name: pipemesh
Version: 1.0
Summary: A package for making pipe network meshes.
Home-page: https://github.com/Duncan-Hunter/pipemesh
Author: Duncan Hunter
Author-email: dunchunter@hotmail.co.uk
License: UNKNOWN
Platform: UNKNOWN
Classifier: Programming Language :: Python :: 3
Classifier: License :: OSI Approved :: GNU General Public License v3 (GPLv3)
Classifier: Operating System :: POSIX :: Linux
